README.md
pyproject.toml
setup.cfg
setup.py
aou_api.egg-info/PKG-INFO
aou_api.egg-info/SOURCES.txt
aou_api.egg-info/dependency_links.txt
aou_api.egg-info/requires.txt
aou_api.egg-info/top_level.txt
aou_api_client/__init__.py
aou_api_client/api_client.py
aou_api_client/api_response.py
aou_api_client/configuration.py
aou_api_client/exceptions.py
aou_api_client/py.typed
aou_api_client/rest.py
aou_api_client/api/__init__.py
aou_api_client/api/access_api.py
aou_api_client/api/access_bibliography_api.py
aou_api_client/api/access_clean_caches_api.py
aou_api_client/api/access_contributors_api.py
aou_api_client/api/access_metadata_api.py
aou_api_client/api/access_monitor_api.py
aou_api_client/api/access_publication_download_api.py
aou_api_client/api/access_settings_api.py
aou_api_client/api/admin_api.py
aou_api_client/api/admin_application_roles_api.py
aou_api_client/api/admin_clean_caches_api.py
aou_api_client/api/admin_contributor_roles_api.py
aou_api_client/api/admin_contributors_api.py
aou_api_client/api/admin_document_file_types_api.py
aou_api_client/api/admin_document_files_api.py
aou_api_client/api/admin_events_api.py
aou_api_client/api/admin_export_metadata_api.py
aou_api_client/api/admin_external_data_api.py
aou_api_client/api/admin_global_banners_api.py
aou_api_client/api/admin_institutions_api.py
aou_api_client/api/admin_languages_api.py
aou_api_client/api/admin_license_groups_api.py
aou_api_client/api/admin_licenses_api.py
aou_api_client/api/admin_modules_api.py
aou_api_client/api/admin_monitor_api.py
aou_api_client/api/admin_notification_types_api.py
aou_api_client/api/admin_notifications_api.py
aou_api_client/api/admin_orcid_api.py
aou_api_client/api/admin_people_api.py
aou_api_client/api/admin_publication_subtypes_api.py
aou_api_client/api/admin_publication_types_api.py
aou_api_client/api/admin_publications_api.py
aou_api_client/api/admin_research_groups_api.py
aou_api_client/api/admin_roles_api.py
aou_api_client/api/admin_scheduled_tasks_api.py
aou_api_client/api/admin_stored_searches_api.py
aou_api_client/api/admin_structures_api.py
aou_api_client/api/admin_system_properties_api.py
